<tns:importInspectionPlanRequest xmlns:base="http://dom.gosuslugi.ru/schema/integration/8.7.0.3/" xmlns:tns="http://dom.gosuslugi.ru/schema/integration/8.7.0.3/inspection/">
  <tns:ImportInspectionPlan>
    <base:TransportGUID></base:TransportGUID>
    <tns:Sign></tns:Sign>
    <tns:InspectionPlan>
      <tns:Year></tns:Year>
      <tns:ApprovalDate></tns:ApprovalDate>
      <tns:AdditionalInfo></tns:AdditionalInfo>
    </tns:InspectionPlan>
    <tns:ImportPlannedExamination>
      <base:TransportGUID></base:TransportGUID>
      <tns:Publish></tns:Publish>
      <tns:PlannedExamination>
        <tns:NumberInPlan></tns:NumberInPlan>
        <tns:Subject>
          <tns:Organization>
            <base:orgRootEntityGUID></base:orgRootEntityGUID>
            <tns:ActualActivityPlace></tns:ActualActivityPlace>
          </tns:Organization>
        </tns:Subject>
        <tns:Objective></tns:Objective>
        <tns:Base>
          <base:Code></base:Code>
          <base:GUID></base:GUID>
          <base:Name></base:Name>
        </tns:Base>
        <tns:DateFrom></tns:DateFrom>
        <tns:Duration>
          <tns:WorkDays></tns:WorkDays>
        </tns:Duration>
        <tns:ExaminationForm>
          <base:Code></base:Code>
          <base:GUID></base:GUID>
          <base:Name></base:Name>
        </tns:ExaminationForm>
      </tns:PlannedExamination>
    </tns:ImportPlannedExamination>
  </tns:ImportInspectionPlan>
</tns:importInspectionPlanRequest>
